<?xml version="1.0" encoding="UTF-8"?><permutation name="BA7141E9A5F5D500331F24B9780DB64F">
<variables>
<mobile.user.agent>mobilesafari</mobile.user.agent>
<user.agent>safari</user.agent>
<mgwt.os>ipad_retina</mgwt.os>
</variables>
<files>
<file>index.html</file>
<file>showcase/BA7141E9A5F5D500331F24B9780DB64F.cache.js</file>
<file>logo.png</file>
<file>./</file>
<file>showcase/compilation-mappings.txt</file>
<file>showcase/showcase.nocache.js</file>
<file>showcase/showcase.devmode.js</file>
<file>showcase/clear.cache.gif</file>
</files>
</permutation>
